locallang/__init__.py
locallang/__main__.py
locallang/lang_init.py
local_lang-0.0.17.dist-info/METADATA
local_lang-0.0.17.dist-info/WHEEL
local_lang-0.0.17.dist-info/entry_points.txt
local_lang-0.0.17.dist-info/licenses/LICENSE
local_lang-0.0.17.dist-info/RECORD
