Metadata-Version: 2.3
Name: local_lang
Version: 0.0.17
Summary: A small package to localise your python application
Project-URL: Homepage, https://github.com/maxland255/localisation_lang
Project-URL: Bug Tracker, https://github.com/maxland255/localisation_lang/issues
Author-email: Maxland255 <developer@pieteraerens.eu>
License:                     GNU GENERAL PUBLIC LICENSE
License-File: LICENSE
Keywords: lang,language,local_lang,localisation,localisation_lang,localization,localization_lang,locallang
Classifier: Development Status :: 4 - Beta
Classifier: License :: OSI Approved :: GNU General Public License v3 (GPLv3)
Classifier: Operating System :: OS Independent
Classifier: Programming Language :: Python :: 3.12
Classifier: Topic :: Software Development :: Localization
Requires-Python: >=3.8
